websocket_rpcs_tool/__config__.py
websocket_rpcs_tool/__main__.py
websocket_rpcs_tool-0.1.0.dist-info/entry_points.txt
websocket_rpcs_tool-0.1.0.dist-info/METADATA
websocket_rpcs_tool-0.1.0.dist-info/WHEEL
websocket_rpcs_tool-0.1.0.dist-info/RECORD
