Metadata-Version: 2.1
Name: websocket-rpcs-tool
Version: 0.1.0
Summary: websocket rpc protobuf generate tool
Author: jawide
Author-email: jawide@qq.com
Requires-Python: >=3.7,<4.0
Classifier: Programming Language :: Python :: 3
Classifier: Programming Language :: Python :: 3.7
Classifier: Programming Language :: Python :: 3.8
Classifier: Programming Language :: Python :: 3.9
Classifier: Programming Language :: Python :: 3.10
Classifier: Programming Language :: Python :: 3.11
Requires-Dist: appdirs (>=1.4.4,<2.0.0)
Requires-Dist: requests (>=2.28.2,<3.0.0)
Requires-Dist: wget (>=3.2,<4.0)
